sql2nosql/__init__.py
sql2nosql/errors.py
sql2nosql/utils.py
sql2nosql-0.3.33.dist-info/LICENSE.txt
sql2nosql-0.3.33.dist-info/METADATA
sql2nosql-0.3.33.dist-info/WHEEL
sql2nosql-0.3.33.dist-info/top_level.txt
sql2nosql-0.3.33.dist-info/RECORD
