Metadata-Version: 2.1
Name: sql2nosql
Version: 0.3.33
Summary: Migrate data from SQL to NoSQL easily
Home-page: https://github.com/facundopadilla/sql2nosql
Author: Facundo Padilla
Author-email: facundo.padilla@outlook.com
License: MIT
Download-URL: https://github.com/facundopadilla/sql2nosql/archive/refs/heads/main.zip
Keywords: sql,nosql,migrator,sql2nosql,migrate
Platform: UNKNOWN
Classifier: Development Status :: 5 - Production/Stable
Classifier: Intended Audience :: Developers
Classifier: Topic :: Software Development :: Build Tools
Classifier: License :: OSI Approved :: MIT License
Classifier: Programming Language :: Python :: 3
Classifier: Programming Language :: Python :: 3.6
Classifier: Programming Language :: Python :: 3.7
Classifier: Programming Language :: Python :: 3.8
Classifier: Programming Language :: Python :: 3.9
License-File: LICENSE.txt
Requires-Dist: simplejson
Requires-Dist: tqdm
